SlickRecorder/SlickRecorder.py
SlickRecorder/__init__.py
SlickRecorder/c_audio_rec.py
SlickRecorder/captions.py
SlickRecorder/cursor1.png
SlickRecorder/cursor2.png
SlickRecorder/cursor3.png
SlickRecorder/cursor4.png
SlickRecorder/cursor5.png
SlickRecorder/cursor6.png
SlickRecorder/cursor7.png
SlickRecorder/gui.py
SlickRecorder/icoon.py
SlickRecorder/keyboard_text.png
SlickRecorder/m_audio_rec.py
SlickRecorder/main.py
SlickRecorder/recorder.py
SlickRecorder/red_dot.png
SlickRecorder/refine.py
SlickRecorder/start_icon.py
SlickRecorder/title.png
SlickRecorder-0.1.dist-info/LICENSE
SlickRecorder-0.1.dist-info/METADATA
SlickRecorder-0.1.dist-info/WHEEL
SlickRecorder-0.1.dist-info/entry_points.txt
SlickRecorder-0.1.dist-info/top_level.txt
SlickRecorder-0.1.dist-info/RECORD
