Metadata-Version: 2.1
Name: SlickRecorder
Version: 0.1
Summary: A Slick screen recorder for linux! With some cool features :]
Home-page: https://github.com/merwin-asm/SlickRecorder
Author: Merwin M
License: MIT
Platform: UNKNOWN
License-File: LICENSE
Requires-Dist: SpeechRecognition
Requires-Dist: moviepy
Requires-Dist: pydub
Requires-Dist: numpy
Requires-Dist: pillow
Requires-Dist: opencv-python
Requires-Dist: pyautogui
Requires-Dist: pynput
Requires-Dist: screeninfo
Requires-Dist: pyaudio
Requires-Dist: PyQt5
Requires-Dist: noisereduce
Requires-Dist: scipy
Requires-Dist: pystray
